moiz_ml_test_othoz/README.pdf
moiz_ml_test_othoz/__init__.py
moiz_ml_test_othoz/dataset_generator.py
moiz_ml_test_othoz/evaluate.py
moiz_ml_test_othoz/evaluation_results.pdf
moiz_ml_test_othoz/requirements.txt
moiz_ml_test_othoz/research_paper.pdf
moiz_ml_test_othoz/settings.py
moiz_ml_test_othoz/train.py
moiz_ml_test_othoz/trained_models.zip
moiz_ml_test_othoz-0.0.1.dist-info/LICENSE
moiz_ml_test_othoz-0.0.1.dist-info/METADATA
moiz_ml_test_othoz-0.0.1.dist-info/WHEEL
moiz_ml_test_othoz-0.0.1.dist-info/top_level.txt
moiz_ml_test_othoz-0.0.1.dist-info/RECORD
