Metadata-Version: 2.1
Name: moiz-ml-test-othoz
Version: 0.0.1
Summary: Implemented addition of two numbers in a sequence of varying length in keras.
Classifier: Programming Language :: Python :: 3
Classifier: License :: OSI Approved :: MIT License
Classifier: Operating System :: OS Independent
Requires-Python: >=3.6
License-File: LICENSE
